haloprops/__init__.py
haloprops/structure.py
haloprops/data/sample_ELUCID_L500_N3072_H10000.h5
haloprops-0.0.1.dist-info/METADATA
haloprops-0.0.1.dist-info/WHEEL
haloprops-0.0.1.dist-info/top_level.txt
haloprops-0.0.1.dist-info/RECORD
