Metadata-Version: 2.1
Name: haloprops
Version: 0.0.1
Summary: relation of halo properties
Home-page: UNKNOWN
Author: Yangyao Chen
Author-email: yangyaochen.astro@foxmail.com
License: UNKNOWN
Platform: UNKNOWN
Requires-Python: >=3.4
Requires-Dist: h5py
Requires-Dist: scikit-learn
Requires-Dist: numpy
Requires-Dist: scipy
